LICENSE
MANIFEST.in
README.md
setup.cfg
setup.py
django_mp_pagination.egg-info/PKG-INFO
django_mp_pagination.egg-info/SOURCES.txt
django_mp_pagination.egg-info/dependency_links.txt
django_mp_pagination.egg-info/top_level.txt
pagination/__init__.py
pagination/mixins.py
pagination/page.py
pagination/paginator.py
pagination/settings.py
pagination/templates/pagination.html