Metadata-Version: 2.1
Name: django-mp-pagination
Version: 0.3.0
Summary: Django pagination app
Home-page: https://github.com/pmaigutyak/mp-pagination
Author: Paul Maigutyak
Author-email: pmaigutyak@gmail.com
License: MIT
Download-URL: https://github.com/pmaigutyak/mp-pagination/archive/0.3.0.tar.gz
Platform: UNKNOWN
License-File: LICENSE
